pyxui/__init__.py
pyxui/xui.py
pyxui/config_gen/__init__.py
pyxui/errors/__init__.py
pyxui/methods/__init__.py
pyxui/methods/base.py
pyxui/methods/clients.py
pyxui/methods/inbounds.py
pyxui/methods/login.py
pyxui-0.0.9.dist-info/LICENSE
pyxui-0.0.9.dist-info/METADATA
pyxui-0.0.9.dist-info/WHEEL
pyxui-0.0.9.dist-info/top_level.txt
pyxui-0.0.9.dist-info/RECORD
