Metadata-Version: 2.1
Name: pyxui
Version: 0.0.9
Summary: An application with python that allows you to modify your xui panel
Home-page: https://github.com/staliox/pyxui
Author: Staliox
License: MIT
Keywords: pyxui,xui,xui python,xui panel
Classifier: Programming Language :: Python :: 3
Classifier: License :: OSI Approved :: MIT License
License-File: LICENSE
Requires-Dist: requests
